pacifica_uploader-0.3.1-py3.8-nspkg.pth
pacifica/uploader/__init__.py
pacifica/uploader/uploader.py
pacifica/uploader/bundler/__init__.py
pacifica/uploader/bundler/bundler.py
pacifica/uploader/common/__init__.py
pacifica/uploader/metadata/__init__.py
pacifica/uploader/metadata/metadata.py
pacifica/uploader/metadata/metaupdate.py
pacifica/uploader/metadata/mjson.py
pacifica/uploader/metadata/policyquery.py
pacifica_uploader-0.3.1.dist-info/LICENSE
pacifica_uploader-0.3.1.dist-info/METADATA
pacifica_uploader-0.3.1.dist-info/WHEEL
pacifica_uploader-0.3.1.dist-info/namespace_packages.txt
pacifica_uploader-0.3.1.dist-info/top_level.txt
pacifica_uploader-0.3.1.dist-info/RECORD
