Metadata-Version: 2.1
Name: pacifica-uploader
Version: 0.3.1
Summary: Pacifica Uploader
Home-page: https://github.com/pacifica/pacifica-python-uploader/
Author: David Brown
Author-email: david.brown@pnnl.gov
License: UNKNOWN
Platform: UNKNOWN
Requires-Dist: requests
